django_huey/__init__.py
django_huey/apps.py
django_huey/config.py
django_huey/exceptions.py
django_huey/models.py
django_huey/utils.py
django_huey/management/__init__.py
django_huey/management/commands/__init__.py
django_huey/management/commands/djangohuey.py
django_huey-1.3.1.dist-info/licenses/LICENCE
tests/__init__.py
tests/queuesinvalid.py
tests/queuesvalid.py
tests/tests_apps.py
tests/tests_config.py
tests/tests_decorators.py
tests/tests_multiqueue.py
django_huey-1.3.1.dist-info/METADATA
django_huey-1.3.1.dist-info/WHEEL
django_huey-1.3.1.dist-info/top_level.txt
django_huey-1.3.1.dist-info/RECORD
